[
  {
    "heading": "Today",
    "text": "Clouds and a few snow showers north, maybe a little sun.\u00a0 Becoming partly sunny south.",
    "temperature": "30s north to low 40s south",
    "icon_url": "https://fairbanksmuseum.org/wp-content/uploads/2023/03/snow_showers_sun.png"
  },
  {
    "heading": "Friday Night",
    "text": "Any flurries giving way to some clearing north. Partly cloudy south.",
    "temperature": "20s, a few teens north",
    "icon_url": "https://fairbanksmuseum.org/wp-content/uploads/2023/03/partly_cloudy_night.png"
  },
  {
    "heading": "Saturday",
    "text": "Partly sunny, then clouds. Some late-day rain or snow in New York.",
    "temperature": "Lower 30s to lower 40s, north to south",
    "icon_url": "https://fairbanksmuseum.org/wp-content/uploads/2023/03/partly_sunny.png"
  },
  {
    "heading": "Sunday",
    "text": "A wintry mix changing to rain and snow.",
    "temperature": "Low to mid 40s, with 30s northeast, and upper 40s far south",
    "icon_url": "https://fairbanksmuseum.org/wp-content/uploads/2023/03/light_winter_mix.png"
  }
]