[
  {
    "heading": "Monday Night",
    "text": "Partly cloudy southeast. Clouds northwest, with a good chance of showers.",
    "temperature": "50s",
    "icon_url": "https://fairbanksmuseum.org/wp-content/uploads/2023/04/showers_night.png"
  },
  {
    "heading": "Tuesday",
    "text": "Showers likely north. Early sun south, scattered afternoon showers.Upper 60s to low 70s",
    "temperature": "",
    "icon_url": "https://fairbanksmuseum.org/wp-content/uploads/2023/03/showers.png"
  },
  {
    "heading": "Wednesday",
    "text": "Clouds, a few showers. A little sun far north.",
    "temperature": "60s to low 70s",
    "icon_url": "https://fairbanksmuseum.org/wp-content/uploads/2023/03/showers.png"
  }
]