[
  {
    "heading": "Today",
    "text": "Some early sun east. Becoming cloudy. Light snow spreading east this afternoon.",
    "temperature": "Teens north to low 20s south",
    "icon_url": "https://fairbanksmuseum.org/wp-content/uploads/2023/03/light_snow.png"
  },
  {
    "heading": "Monday Night",
    "text": "Evening snow ending. Some breaks late.",
    "temperature": "Teens, some single digits far north",
    "icon_url": "https://fairbanksmuseum.org/wp-content/uploads/2023/03/snow_light_night.png"
  },
  {
    "heading": "Tuesday",
    "text": "Early sun, then clouds. Snow or freezing rain west late.",
    "temperature": "Upper 20s to mid 30s",
    "icon_url": "https://fairbanksmuseum.org/wp-content/uploads/2023/03/mostly_cloudy.png"
  },
  {
    "heading": "Wednesday",
    "text": "Snow northeast, a wintry mix southwest, tapering off.",
    "temperature": "30s to near 40",
    "icon_url": "https://fairbanksmuseum.org/wp-content/uploads/2023/03/light_winter_mix.png"
  }
]