[
  {
    "heading": "Saturday",
    "text": "Scattered valley rain and mountain snow showers, mainly north.",
    "temperature": "Upper 30s to upper 40s north to south",
    "icon_url": "https://fairbanksmuseum.org/wp-content/uploads/2023/03/snow_rain_showers.png"
  },
  {
    "heading": "Tonight",
    "text": "Mostly cloudy north, some clearing south. Breezy.",
    "temperature": "30s, upper 20s in the cold hollows",
    "icon_url": "https://fairbanksmuseum.org/wp-content/uploads/2023/03/mostly_cloudy_night.png"
  },
  {
    "heading": "Sunday",
    "text": "Sunny south. Morning clouds north, more afternoon sun.",
    "temperature": "40s",
    "icon_url": "https://fairbanksmuseum.org/wp-content/uploads/2023/03/partly_sunny.png"
  },
  {
    "heading": "Monday",
    "text": "Clouds building west to east early, increased chance of showers late.",
    "temperature": "",
    "icon_url": "https://fairbanksmuseum.org/wp-content/uploads/2023/03/cloudy.png"
  }
]